README.txt
setup.py
Products/__init__.py
Products.ExternalStorage.egg-info/PKG-INFO
Products.ExternalStorage.egg-info/SOURCES.txt
Products.ExternalStorage.egg-info/dependency_links.txt
Products.ExternalStorage.egg-info/entry_points.txt
Products.ExternalStorage.egg-info/namespace_packages.txt
Products.ExternalStorage.egg-info/not-zip-safe
Products.ExternalStorage.egg-info/requires.txt
Products.ExternalStorage.egg-info/top_level.txt
Products/ExternalStorage/ExternalStorage.py
Products/ExternalStorage/Makefile
Products/ExternalStorage/__init__.py
Products/ExternalStorage/config.py
Products/ExternalStorage/filewrapper.py
Products/ExternalStorage/utils.py
Products/ExternalStorage/example/ExternalExample/ComplexSample.py
Products/ExternalStorage/example/ExternalExample/ExternalArticle.py
Products/ExternalStorage/example/ExternalExample/ExternalImage.py
Products/ExternalStorage/example/ExternalExample/README
Products/ExternalStorage/example/ExternalExample/StreamingFile.py
Products/ExternalStorage/example/ExternalExample/__init__.py
Products/ExternalStorage/example/ExternalExample/config.py
Products/ExternalStorage/example/ExternalExample/refresh.txt
Products/ExternalStorage/example/ExternalExample/Extensions/Install.py
Products/ExternalStorage/example/ExternalExample/skins/externalexample/article_view.pt
Products/ExternalStorage/interfaces/__init__.py
Products/ExternalStorage/interfaces/externalstorage.py
Products/ExternalStorage/tests/ESTestCase.py
Products/ExternalStorage/tests/__init__.py
Products/ExternalStorage/tests/dummy.py
Products/ExternalStorage/tests/testAdd.py
Products/ExternalStorage/tests/testArchive.py
Products/ExternalStorage/tests/testContentType.py
Products/ExternalStorage/tests/testCopy.py
Products/ExternalStorage/tests/testCut.py
Products/ExternalStorage/tests/testDelete.py
Products/ExternalStorage/tests/testEdit.py
Products/ExternalStorage/tests/testExternalStorage.py
Products/ExternalStorage/tests/testFilename.py
Products/ExternalStorage/tests/testFunctional.py
Products/ExternalStorage/tests/testImageField.py
Products/ExternalStorage/tests/testMultiField.py
Products/ExternalStorage/tests/testRename.py
Products/ExternalStorage/tests/data/sample (chars).zip
Products/ExternalStorage/tests/data/sample.png
Products/ExternalStorage/tests/data/sample.zip
Products/ExternalStorage/tests/data/test (chars).doc
