Metadata-Version: 1.0
Name: Products.ExternalStorage
Version: 0.8.1
Summary: An add-on Plone product which provides an extra storage for Archetypes.
Home-page: http://plone.org/products/externalstorage
Author: Dorneles Treméa
Author-email: deo@plonesolutions.com
License: Custom
Keywords: Plone Archetypes ExternalStorage
Platform: UNKNOWN
Classifier: Programming Language :: Python
Classifier: Topic :: Software Development :: Libraries :: Python Modules
Classifier: Framework :: Plone
